serifan/__init__.py
serifan/comic.py
serifan/comics_list.py
serifan/exceptions.py
serifan/session.py
serifan/utils.py
serifan-1.0.6.dist-info/LICENSE
serifan-1.0.6.dist-info/WHEEL
serifan-1.0.6.dist-info/METADATA
serifan-1.0.6.dist-info/RECORD
