Metadata-Version: 2.1
Name: serifan
Version: 1.0.6
Summary: Python wrapper for the Shortboxed API
License: GPL-3.0-or-later
Keywords: comics,comic
Author: Brian Pepple
Author-email: bdpepple@gmail.com
Maintainer: Brian Pepple
Maintainer-email: bdpepple@gmail.com
Requires-Python: >=3.7,<4.0
Classifier: Development Status :: 5 - Production/Stable
Classifier: Intended Audience :: Developers
Classifier: License :: OSI Approved :: GNU General Public License v3 or later (GPLv3+)
Classifier: Natural Language :: English
Classifier: Programming Language :: Python :: 3
Classifier: Programming Language :: Python :: 3.7
Classifier: Programming Language :: Python :: 3.8
Classifier: Programming Language :: Python :: 3.9
Classifier: Topic :: Internet
Classifier: Topic :: Software Development :: Libraries :: Python Modules
Provides-Extra: docs
Requires-Dist: marshmallow (>=3.13.0,<4.0.0)
Requires-Dist: requests (>=2.26.0,<3.0.0)
Requires-Dist: sphinx-rtd-theme (>=0.5.2,<0.6.0); extra == "docs"
Requires-Dist: sphinxcontrib-napoleon (>=0.7,<0.8); extra == "docs"
Project-URL: Bug Tracker, https://github.com/bpepple/serifan/issues
Project-URL: Homepage, https://github.com/bpepple/serifan
